Metadata-Version: 2.1
Name: coover-thumbor-plugins
Version: 0.4
Summary: Thumbor Coover plugins
Home-page: UNKNOWN
Author: ViZeke & Alvarollmenezes
Author-email: vizeke@gmail.com
License: UNKNOWN
Keywords: thumbor aws
Platform: UNKNOWN
Classifier: Development Status :: 5 - Production/Stable
Classifier: Intended Audience :: Developers
Classifier: License :: OSI Approved :: MIT License
Classifier: Operating System :: OS Independent
Classifier: Topic :: Software Development :: Libraries :: Python Modules
Classifier: Topic :: Internet
Classifier: Programming Language :: Python :: 2
Classifier: Programming Language :: Python :: 2.7
Provides-Extra: tests
